pixelveil-1.0.1.dist-info/METADATA
pixelveil-1.0.1.dist-info/WHEEL
pixelveil-1.0.1.dist-info/licenses/LICENSE
pixelveil/__init__.py
pixelveil/__init__.pyi
pixelveil/bpcs.py
pixelveil/bpcs.pyi
pixelveil/image_steganalysis.py
pixelveil/image_steganalysis.pyi
pixelveil/image_utils.py
pixelveil/image_utils.pyi
pixelveil/pixelveil.cpython-314-x86_64-linux-gnu.so
pixelveil-1.0.1.dist-info/RECORD
