Metadata-Version: 2.4
Name: pixelveil
Version: 1.0.1
License-File: LICENSE
Summary: A performant steganography and steganalysis library for hiding data in images, audio files, and videos
Author-email: Jebbex <107323805+Jebbex1@users.noreply.github.com>
License: MIT
Requires-Python: >=3.13
